NanaoLink/Repeat.py
NanaoLink/__init__.py
NanaoLink/autoplay.py
NanaoLink/filters.py
NanaoLink/infoTrack.py
NanaoLink/node.py
NanaoLink/player.py
NanaoLink-0.1.1.dist-info/LICENSE
NanaoLink-0.1.1.dist-info/METADATA
NanaoLink-0.1.1.dist-info/WHEEL
NanaoLink-0.1.1.dist-info/top_level.txt
NanaoLink-0.1.1.dist-info/RECORD
