Metadata-Version: 2.1
Name: NanaoLink
Version: 0.1.1
Summary: แพ็กเกจ client สำหรับ lavalink ที่ปรับให้ใช้งานง่ายขึ้น
Author: NekoSakuraLucia
License: MIT
Project-URL: repositroy, https://github.com/NekoSakuraLucia/NanaoLink
Requires-Python: >=3.10
License-File: LICENSE
Requires-Dist: wavelink
